Workbook

Sheet 1. Personal Budget
A1: 💸 PERSONAL BUDGET | Monthly Expenses
A3: Expense | B3: Monthly (£) | C3: Annual (£) | D3: Notes
A4: Rent | B4: 2650 | C4: =B4*12 | D4: Monthly rent
A5: Council Tax | B5: 150 | C5: =B5*12
A6: Utilities | B6: 250 | C6: =B6*12 | D6: Gas, electric, broadband
A7: Food & Groceries | B7: 300 | C7: =B7*12
A8: Transport | B8: 100 | C8: =B8*12 | D8: Travel card / fuel
A9: Gym | B9: 125 | C9: =B9*12
A10: Supplements | B10: 75 | C10: =B10*12
A11: Medication | B11: 50 | C11: =B11*12
A12: Social | B12: 250 | C12: =B12*12 | D12: Eating out, entertainment
A13: Travel | B13: 100 | C13: =B13*12 | D13: Holidays / weekends away
A14: TOTAL MONTHLY | B14: =SUM(B4:B13) | C14: =SUM(C4:C13)
A16: ⚡ Milestone 1 target: £4,050/mo personal income (salary + dividends after tax)

Sheet 2. Business P&L
A1: 📊 BUSINESS P&L | Monthly Tracker 2026
A3: Line Item | B3: Default/Notes | C3: Jan | D3: Feb | E3: Mar | F3: Apr | G3: May | H3: Jun | I3: Jul | J3: Aug | K3: Sep | L3: Oct | M3: Nov | N3: Dec | O3: YTD Total
A4: Revenue | B4: ← Enter monthly revenue | C4: 0 | D4: 0 | E4: 0 | F4: 0 | G4: 0 | H4: 0 | I4: 0 | J4: 0 | K4: 0 | L4: 0 | M4: 0 | N4: 0 | O4: =SUM(C4:N4)
A5: BUSINESS COSTS
A6: Website | B6: £20/mo — Hosting / domain | C6: 20 | D6: 20 | E6: 20 | F6: 20 | G6: 20 | H6: 20 | I6: 20 | J6: 20 | K6: 20 | L6: 20 | M6: 20 | N6: 20 | O6: =SUM(C6:N6)
A7: Email | B7: £20/mo — GSuite / Outlook | C7: 20 | D7: 20 | E7: 20 | F7: 20 | G7: 20 | H7: 20 | I7: 20 | J7: 20 | K7: 20 | L7: 20 | M7: 20 | N7: 20 | O7: =SUM(C7:N7)
A8: AI Tools | B8: £180/mo — ChatGPT Plus, Claude etc. | C8: 180 | D8: 180 | E8: 180 | F8: 180 | G8: 180 | H8: 180 | I8: 180 | J8: 180 | K8: 180 | L8: 180 | M8: 180 | N8: 180 | O8: =SUM(C8:N8)
A9: Expandi | B9: £75/mo — LinkedIn automation | C9: 75 | D9: 75 | E9: 75 | F9: 75 | G9: 75 | H9: 75 | I9: 75 | J9: 75 | K9: 75 | L9: 75 | M9: 75 | N9: 75 | O9: =SUM(C9:N9)
A10: PhantomBuster | B10: £75/mo — Web scraping / automation | C10: 75 | D10: 75 | E10: 75 | F10: 75 | G10: 75 | H10: 75 | I10: 75 | J10: 75 | K10: 75 | L10: 75 | M10: 75 | N10: 75 | O10: =SUM(C10:N10)
A11: Calendly | B11: £10/mo — Scheduling | C11: 10 | D11: 10 | E11: 10 | F11: 10 | G11: 10 | H11: 10 | I11: 10 | J11: 10 | K11: 10 | L11: 10 | M11: 10 | N11: 10 | O11: =SUM(C11:N11)
A12: LinkedIn Premium | B12: £100/mo — Sales Navigator | C12: 100 | D12: 100 | E12: 100 | F12: 100 | G12: 100 | H12: 100 | I12: 100 | J12: 100 | K12: 100 | L12: 100 | M12: 100 | N12: 100 | O12: =SUM(C12:N12)
A13: Total Business Costs | B13: £480/mo default | C13: =SUM(C6:C12) | D13: =SUM(D6:D12) | E13: =SUM(E6:E12) | F13: =SUM(F6:F12) | G13: =SUM(G6:G12) | H13: =SUM(H6:H12) | I13: =SUM(I6:I12) | J13: =SUM(J6:J12) | ... N13: =SUM(N6:N12) | O13: =SUM(C13:N13)
A14: PROFIT & TAX
A15: Gross Profit (Revenue − Costs) | B15: =Revenue − Total Costs | C15: =C4-C13 | D15: =D4-D13 | E15: =E4-E13 | F15: =F4-F13 | G15: =G4-G13 | H15: =H4-H13 | I15: =I4-I13 | J15: =J4-J13 | ... N15: =N4-N13 | O15: =SUM(C15:N15)
A16: Corporation Tax (25%) | B16: 25% of Gross Profit | C16: =IF(C15>0,C15*0.25,0) | D16: =IF(D15>0,D15*0.25,0) | E16: =IF(E15>0,E15*0.25,0) | F16: =IF(F15>0,F15*0.25,0) | G16: =IF(G15>0,G15*0.25,0) | H16: =IF(H15>0,H15*0.25,0) | I16: =IF(I15>0,I15*0.25,0) | J16: =IF(J15>0,J15*0.25,0) | ... N16: =IF(N15>0,N15*0.25,0) | O16: =SUM(C16:N16)
A17: Net Profit After Tax | B17: Gross Profit − Corp Tax | C17: =C15-C16 | D17: =D15-D16 | E17: =E15-E16 | F17: =F15-F16 | G17: =G15-G16 | H17: =H15-H16 | I17: =I15-I16 | J17: =J15-J16 | ... N17: =N15-N16 | O17: =SUM(C17:N17)

Sheet 3. Tax & Draw
A1: 🏛️ TAX & DRAW STRUCTURE | UK Ltd (Sole Director)
A3: Line Item | B3: Annual (£) | C3: Monthly (£) | D3: Notes
A5: INPUT ASSUMPTIONS (yellow = adjust these)
A6: Annual Gross Revenue | B6: 60000 | C6: =B6/12 | D6: Total business revenue
A7: Total Business Costs (pa) | B7: 5760 | C7: =B7/12 | D7: £480/mo × 12
A8: Director Salary (annual) | B8: 12570 | C8: =B8/12 | D8: ⬅️ ADJUSTABLE — default = personal allowance
A9: NI Secondary Threshold | B9: 9100 | C9: =B9/12 | D9: 2025/26 employer NI threshold
A10: Employer NI Rate | B10: 0.1505 | D10: 15.05% on salary above threshold
A11: Corporation Tax Rate | B11: 0.25 | D11: 25% main rate
A12: Dividend Allowance | B12: 1000 | C12: =B12/12 | D12: Tax-free dividend allowance
A13: Basic Rate Div Tax | B13: 0.0875 | D13: 8.75% on divs (basic rate band)
A14: Higher Rate Div Tax | B14: 0.3375 | D14: 33.75% on divs (higher rate band)
A15: Basic Rate Upper Limit | B15: 50270 | C15: =B15/12 | D15: Total income threshold (basic/higher rate)
A17: TAX & DRAW WATERFALL
A18: Gross Revenue | B18: =B6 | C18: =B18/12 | D18: Business revenue before anything
A19: Less: Business Costs | B19: =-B7 | C19: =B19/12 | D19: Operating expenses
A20: =Gross Profit | B20: =B18+B19 | C20: =B20/12 | D20: Revenue after costs, before tax/pay
A21: Less: Corporation Tax (25%) | B21: =IF(B20>0,-B20*B11,0) | C21: =B21/12 | D21: 25% of gross profit
A22: =Net Profit After Corp Tax | B22: =B20+B21 | C22: =B22/12 | D22: What's left after corp tax
A23: Less: Director Salary | B23: =-B8 | C23: =B23/12 | D23: Salary paid to director (deductible cost)
A24: Less: Employer NI on Salary | B24: =IF(B8>B9,-((B8-B9)*B10),0) | C24: =B24/12 | D24: NI on salary above £9,100
A25: =Profit Available for Divs | B25: =B22+B23+B24 | C25: =B25/12 | D25: After salary & NI deducted
A27: Director Income: Salary | B27: =B8 | C27: =B27/12 | D27: Salary received
A28: Director Income: Dividends | B28: =MAX(0,B25) | C28: =B28/12 | D28: All available profit taken as dividends
A29: Total Pre-Tax Income | B29: =B27+B28 | C29: =B29/12 | D29: Salary + dividends
A31: Income Tax on Salary | B31: =0 | C31: =B31/12 | D31: £0 — salary = personal allowance
A32: Dividend Tax: Free Allowance | B32: =-MIN(B28,B12) | C32: =B32/12 | D32: First £1,000 tax free
A33: Taxable Dividends | B33: =MAX(0,B28-B12) | C33: =B33/12 | D33: Divs above £1,000 allowance
A34: Div Tax (Basic Rate 8.75%) | B34: =IF(B29<=B15,-MAX(0,B33)*B13,IF(B33>0,-MIN(B33,B15-B27)*B13,0)) | C34: =B34/12 | D34: 8.75% up to higher rate threshold
A35: Div Tax (Higher Rate 33.75%) | B35: =IF(B29>B15,-MAX(0,B29-B15)*B14,0) | C35: =B35/12 | D35: 33.75% above £50,270 total income
A36: Total Tax | B36: =B31+B34+B35 | C36: =B36/12 | D36: Income tax + dividend tax
A38: NET PERSONAL INCOME | B38: =B29+B36 | C38: =B38/12 | D38: Take-home after all taxes
A39: Effective Tax Rate | B39: =IF(B29>0,(B29-B38)/B29,0) | D39: Total taxes ÷ gross income

Sheet 4. The Bridge
A1: 🌉 THE BRIDGE | Monthly Cash Flow
A3: Line Item | B3: Amount (£) | C3: Monthly (£) | D3: Notes
A5: FROM THE BUSINESS
A6: Business Net Profit (this month) | B6: ='2. Business P&L'!O16 | C6: =B6/12 | D6: From Tab 2 — enter actual month
A7: Director Salary (monthly) | B7: =-'3. Tax & Draw'!C23 | D7: From Tab 3 salary ÷ 12
A8: Dividends Drawn (this month) | B8: 0 | D8: ⬅️ ADJUSTABLE — enter dividends drawn
A9: Retained in Business | B9: =C6-B7-B8 | D9: Remaining profit left in company
A11: PERSONAL INCOME
A12: Salary Received | B12: =B7
A13: Dividends Received | B13: =B8
A14: Dividend Tax Due | B14: =IF(B8>'3. Tax & Draw'!B12,-MAX(0,B8-'3. Tax & Draw'!B12)*'3. Tax & Draw'!B13,0) | D14: Simplified: 8.75% on divs above £1k allowance
A15: NET PERSONAL INCOME | B15: =B12+B13+B14
A17: MONTHLY ALLOCATION
A18: Living Expenses | B18: 4050 | D18: From Tab 1 total
A19: Emergency Fund (monthly) | B19: 200 | D19: ⬅️ ADJUSTABLE — target amount
A20: House Deposit (monthly) | B20: 500 | D20: ⬅️ ADJUSTABLE — target amount
A21: Investing (monthly) | B21: 200 | D21: ⬅️ ADJUSTABLE — ISA / stocks
A22: Discretionary | B22: 200 | D22: ⬅️ ADJUSTABLE — fun money
A23: Total Allocated | B23: =SUM(B18:B22)
A25: ⚡ SURPLUS / DEFICIT
A26: Surplus / (Deficit) | B26: =B15-B23 | D26: Positive = you have headroom. Negative = need more revenue.

Sheet 5. Milestones
A1: 🏆 MILESTONES | Revenue Needed to Hit Each Level
A2: 💡 KEY INSIGHT: £4,530 personal need ≠ £4,530 gross revenue. The business must earn MORE to deliver that net income after Corp Tax, Employer NI, and Dividend Tax.
A4: SHARED INPUTS (from Tab 3)
A5: Corp Tax Rate | B5: ='3. Tax & Draw'!B11
A6: Employer NI Rate | B6: ='3. Tax & Draw'!B10
A7: NI Threshold (annual) | B7: ='3. Tax & Draw'!B9
A8: Annual Salary | B8: ='3. Tax & Draw'!B8
A9: Monthly Biz Costs | B9: 480
A10: Dividend Tax Rate | B10: ='3. Tax & Draw'!B13
A11: Dividend Allowance | B11: ='3. Tax & Draw'!B12
A13: Milestone | B13: Personal Need /mo | C13: Biz Costs /mo | D13: Gross Revenue Needed /mo | E13: What this unlocks
A14: HOW GROSS REVENUE IS CALCULATED: Personal need + biz costs = net business income needed. Gross Revenue = Net Income ÷ (1 − Corp Tax Rate). This covers corp tax. Salary NI is baked into the cost. Dividend tax reduces take-home.
A15: M1 — Survival | B15: 4050 | C15: ='5. Milestones'!B9 | D15: =ROUND((B15+C15)/(1-$B$5),0) | E15: Covers living + biz costs. Just above water.
A16: M2 — Building | B16: 4250 | C16: ='5. Milestones'!B9 | D16: =ROUND((B16+C16)/(1-$B$5),0) | E16: M1 + £200/mo emergency fund
A17: M3 — House Deposit | B17: 4750 | C17: ='5. Milestones'!B9 | D17: =ROUND((B17+C17)/(1-$B$5),0) | E17: M2 + £500/mo house deposit contribution
A18: M4 — Thriving | B18: 5400 | C18: ='5. Milestones'!B9 | D18: =ROUND((B18+C18)/(1-$B$5),0) | E18: M3 + investing + discretionary
A20: 📝 NOTE ON REVERSE CALC: Formula used = (Personal Need + Biz Costs) ÷ (1 − Corp Tax Rate). This is directionally accurate. For precision, account for Employer NI on salary and dividend tax at your marginal rate. Use Tab 3 for exact modelling at specific revenue levels.
A22: MILESTONE TARGETS QUICK REFERENCE
A23: M1 Survival | B23: =D15 | C23: / mo gross revenue | D23: Just covering life and the business
A24: M2 Building | B24: =D16 | C24: / mo gross revenue | D24: Adding emergency savings buffer
A25: M3 House Deposit | B25: =D17 | C25: / mo gross revenue | D25: Saving towards £65k deposit
A26: M4 Thriving | B26: =D18 | C26: / mo gross revenue | D26: Investing + discretionary on top

Sheet 6. Projections
A1: 📈 PROJECTIONS | Revenue Scenarios
A3: INPUT ASSUMPTIONS (yellow = adjust these)
A4: Price per Client — Current (£297) | B4: 297 | E4: Founding member price
A5: Price per Client — Post-Founders (£597) | B5: 597 | E5: Full price after founder cohort
A6: Price per Client — Scaled | B6: 997 | E6: Premium / group programme price
A7: Show Rate (% of leads who show) | B7: 0.6 | E7: 60% default
A8: Close Rate (% of shows who buy) | B8: 0.33 | E8: 33% default
A9: Monthly Outreach Volume (leads) | B9: 100 | E9: Leads contacted per month
A10: Clients / Month (shows × close rate) | B10: =ROUND(B9*B7*B8,0) | E10: Calculated from outreach × show rate × close rate
A12: Scenario | B12: Clients/mo | C12: Monthly Revenue | D12: Annual Revenue | E12: Milestone Hit
A13: Current — Founders (£297) | B13: =B10 | C13: =C13*B4 | D13: =C13*12 | E13: =IF(C13>='5. Milestones'!D18,"M4 — Thriving 🚀",IF(C13>='5. Milestones'!D17,"M3 — House Deposit 🏠",IF(C13>='5. Milestones'!D16,"M2 — Building 📈",IF(C13>='5. Milestones'!D15,"M1 — Survival ✅","Below M1 ⚠️"))))
A14: Stretch — Founders (£297) | B14: =B10*1.5 | C14: =C14*B4 | D14: =C14*12 | E14: =IF(C14>='5. Milestones'!D18,"M4 — Thriving 🚀",IF(C14>='5. Milestones'!D17,"M3 — House Deposit 🏠",IF(C14>='5. Milestones'!D16,"M2 — Building 📈",IF(C14>='5. Milestones'!D15,"M1 — Survival ✅","Below M1 ⚠️"))))
A15: Post-Founders (£597) | B15: =B10 | C15: =C15*B5 | D15: =C15*12 | E15: =IF(C15>='5. Milestones'!D18,"M4 — Thriving 🚀",IF(C15>='5. Milestones'!D17,"M3 — House Deposit 🏠",IF(C15>='5. Milestones'!D16,"M2 — Building 📈",IF(C15>='5. Milestones'!D15,"M1 — Survival ✅","Below M1 ⚠️"))))
A16: Post-Founders Stretch | B16: =B10*1.5 | C16: =C16*B5 | D16: =C16*12 | E16: =IF(C16>='5. Milestones'!D18,"M4 — Thriving 🚀",IF(C16>='5. Milestones'!D17,"M3 — House Deposit 🏠",IF(C16>='5. Milestones'!D16,"M2 — Building 📈",IF(C16>='5. Milestones'!D15,"M1 — Survival ✅","Below M1 ⚠️"))))
A17: Scaled (£997) | B17: =B10 | C17: =C17*B6 | D17: =C17*12 | E17: =IF(C17>='5. Milestones'!D18,"M4 — Thriving 🚀",IF(C17>='5. Milestones'!D17,"M3 — House Deposit 🏠",IF(C17>='5. Milestones'!D16,"M2 — Building 📈",IF(C17>='5. Milestones'!D15,"M1 — Survival ✅","Below M1 ⚠️"))))
A18: Scaled Stretch | B18: =B10*2 | C18: =C18*B6 | D18: =C18*12 | E18: =IF(C18>='5. Milestones'!D18,"M4 — Thriving 🚀",IF(C18>='5. Milestones'!D17,"M3 — House Deposit 🏠",IF(C18>='5. Milestones'!D16,"M2 — Building 📈",IF(C18>='5. Milestones'!D15,"M1 — Survival ✅","Below M1 ⚠️"))))
A20: MILESTONE BREAK-EVEN: Clients Needed per Price Point
A21: Milestone | B21: Monthly Revenue Target | C21: @ £297/client | D21: @ £597/client | E21: @ £997/client
A22: M1 — Survival | B22: ='5. Milestones'!D15 | C22: =CEILING(B22/B4,1) | D22: =CEILING(B22/B5,1) | E22: =CEILING(B22/B6,1)
A23: M2 — Building | B23: ='5. Milestones'!D16 | C23: =CEILING(B23/B4,1) | D23: =CEILING(B23/B5,1) | E23: =CEILING(B23/B6,1)
A24: M3 — House Deposit | B24: ='5. Milestones'!D17 | C24: =CEILING(B24/B4,1) | D24: =CEILING(B24/B5,1) | E24: =CEILING(B24/B6,1)
A25: M4 — Thriving | B25: ='5. Milestones'!D18 | C25: =CEILING(B25/B4,1) | D25: =CEILING(B25/B5,1) | E25: =CEILING(B25/B6,1)
